[{"type": "title", "data": "=Attributes!B2"}, {"type": "category", "data": "Patient Care"}, {"type": "sentence", "data": "None"}, {"type": "order", "data": "Apply Cervical Collar", "value": "checked"}, {"type": "sentence", "data": "T;N"}, {"type": "order", "data": "Cervical Collar Care", "value": "checked"}, {"type": "sentence", "data": "T;N"}, {"type": "sentence", "data": "None"}, {"type": "sentence", "data": "None"}, {"type": "sentence", "data": "None"}, {"type": "sentence", "data": "None"}, {"type": "sentence", "data": "None"}, {"type": "sentence", "data": "None"}, {"type": "sentence", "data": "None"}, {"type": "sentence", "data": "None"}, {"type": "sentence", "data": "None"}, {"type": "sentence", "data": "None"}, {"type": "sentence", "data": "None"}]
