[{"type": "title", "data": "MH cloZAPine q3day Titration"}, {"type": "category", "data": "Patient Care"}, {"type": "note", "data": "Ensure cloZAPine Monitoring PowerPlan has been ordered prior to initiating titration", "value": ""}, {"type": "category", "data": "Medications"}, {"type": "note", "data": "Select only one cloZAPine module below and ensure correct brand is selected", "value": ""}, {"type": "note", "data": "MH cloZAPine (APO or AA PHARMA) (Custom q3day) (Module)", "value": ""}, {"type": "sub phase", "data": "MH cloZAPine (APO or AA PHARMA) (Custom q3day) (Module)", "value": ""}, {"type": "note", "data": "MH cloZAPine (GENPHARM or MYLAN q3day) (Custom) (Module)", "value": ""}, {"type": "sub phase", "data": "MH cloZAPine (GENPHARM or MYLAN) (Custom q3day) (Module)", "value": ""}, {"type": "note", "data": "MH cloZAPine (NOVARTIS or HLS)  (Custom q3day) (Module)", "value": ""}, {"type": "sub phase", "data": "MH cloZAPine (NOVARTIS or HLS) (Custom q3day) (Module)", "value": ""}]
