[{"type": "title", "data": "=Attributes!B2"}, {"type": "category", "data": "Laboratory"}, {"type": "sentence", "data": "None"}, {"type": "order", "data": "CBC and Differential", "value": "checked"}, {"type": "sentence", "data": "Blood, Routine, Unit Collect: No, Collection: T;N, once, order for future visit"}, {"type": "order", "data": "PTT ", "value": "checked"}, {"type": "sentence", "data": "Blood, Routine, Unit Collect: No, Collection: T;N, once, order for future visit"}, {"type": "order", "data": "INR", "value": "checked"}, {"type": "sentence", "data": "Blood, Routine, Unit Collect: No, Collection: T;N, once, order for future visit"}, {"type": "order", "data": "Ferritin", "value": ""}, {"type": "sentence", "data": "Blood, Routine, Unit Collect: No, Collection: T;N, once, order for future visit"}, {"type": "order", "data": "ABO and Rh group (CWH)", "value": ""}, {"type": "sentence", "data": "Blood, Routine, Unit Collect: No, Collection: T;N, once, order for future visit"}, {"type": "order", "data": "ABO and Rh group", "value": ""}, {"type": "sentence", "data": "Blood, Routine, Unit Collect: No, Collection: T;N, once, order for future visit"}, {"type": "order", "data": "ABO/Rh Transplant", "value": ""}, {"type": "sentence", "data": "Blood, Routine, Unit Collect: No, Collection: T;N, once, order for future visit"}, {"type": "order", "data": "Urea and Creatinine Panel", "value": "checked"}, {"type": "sentence", "data": "Blood, Routine, Unit Collect: No, Collection: T;N, once, order for future visit"}, {"type": "order", "data": "Electrolyutes Panel Outpatient", "value": "checked"}, {"type": "sentence", "data": "Blood, Routine, Unit Collect: No, Collection: T;N, once, order for future visit"}, {"type": "order", "data": "Magnesium Level", "value": ""}, {"type": "sentence", "data": "Blood, Routine, Unit Collect: No, Collection: T;N, once, order for future visit"}, {"type": "order", "data": "Calcium Level", "value": ""}, {"type": "sentence", "data": "Blood, Routine, Unit Collect: No, Collection: T;N, once, order for future visit"}, {"type": "order", "data": "Phosphate Level", "value": ""}, {"type": "sentence", "data": "Blood, Routine, Unit Collect: No, Collection: T;N, once, order for future visit"}, {"type": "order", "data": "Lactate Dehydrogenase", "value": ""}, {"type": "sentence", "data": "Blood, Routine, Unit Collect: No, Collection: T;N, once, order for future visit"}, {"type": "order", "data": "Hb Fractionation HPLC", "value": ""}, {"type": "sentence", "data": "Blood, Routine, Unit Collect: No, Collection: T;N, once, order for future visit"}, {"type": "order", "data": "HCG Quantitative Blood", "value": ""}, {"type": "sentence", "data": "Blood, Routine, Unit Collect: No, Collection: T;N, once, order for future visit"}, {"type": "order", "data": "HCG Quantitative Blood", "value": ""}, {"type": "sentence", "data": "Blood, Routine, Unit Collect: No, Collection: T;N, once, order for future visit"}, {"type": "order", "data": "HCG Quantitative Blood", "value": ""}, {"type": "sentence", "data": "Blood, Routine, Unit Collect: No, Collection: T;N, once, order for future visit"}, {"type": "order", "data": "HLA Typing", "value": ""}, {"type": "sentence", "data": "Blood, Routine, Unit Collect: No, Collection: T;N, once, order for future visit"}, {"type": "order", "data": "Chimerism Molecular PED - Pre Transplant", "value": "checked"}, {"type": "sentence", "data": "Blood, Routine, Unit Collect: No, Collection: T;N, once, order for future visit"}, {"type": "order", "data": "Urinalysis Macroscopic (dipstick) with culture if indicated", "value": ""}, {"type": "sentence", "data": "Urine, Routine, Unit Collect: No, Collection:T;N, once, order for future visit"}, {"type": "subphase", "data": "LAB - PEDS Allogeneic Infectious Disease Screening for Bone Marrow Transplant (BMT)", "value": ""}, {"type": "sentence", "data": "None"}, {"type": "category", "data": "Consults / Referrals"}, {"type": "sentence", "data": "None"}, {"type": "note", "data": "Consider consultation with Anesthesia", "value": ""}, {"type": "sentence", "data": "None"}, {"type": "sentence", "data": "None"}, {"type": "sentence", "data": "None"}, {"type": "sentence", "data": "None"}, {"type": "sentence", "data": "None"}, {"type": "sentence", "data": "None"}, {"type": "sentence", "data": "None"}, {"type": "sentence", "data": "None"}, {"type": "sentence", "data": "None"}, {"type": "sentence", "data": "None"}, {"type": "sentence", "data": "None"}, {"type": "sentence", "data": "None"}, {"type": "sentence", "data": "None"}, {"type": "sentence", "data": "None"}, {"type": "sentence", "data": "None"}, {"type": "sentence", "data": "None"}]
