[{"type": "title", "data": "NICU Endotracheal Intubation (Module)"}, {"type": "category", "data": "Admit/Transfer/Discharge"}, {"type": "note", "data": "Refer to Endotracheal Intubation Policy and Procedure", "value": ""}, {"type": "category", "data": "Patient Care"}, {"type": "order", "data": "Critical Care Goals", "value": "checked"}, {"type": "sentence", "data": "SpO2 goal: 88% to 92%, for infants PMA less than or equal to 36 weeks"}, {"type": "sentence", "data": "SpO2 goal: 90% to 94%, for infants PMA greater than 36 weeks"}, {"type": "category", "data": "Medications"}, {"type": "order", "data": "atropine", "value": "checked"}, {"type": "sentence", "data": "0.02 mg/kg, IV, as directed, drug form: inj"}, {"type": "order", "data": "fentanyl", "value": "checked"}, {"type": "sentence", "data": "3 mcg/kg, IV, as directed, drug form: inj"}, {"type": "order", "data": "succinylcholine", "value": "checked"}, {"type": "sentence", "data": "2 mg/kg, IV, as directed, drug form: inj"}, {"type": "order", "data": "succinylcholine", "value": "checked"}, {"type": "sentence", "data": "2 mg/kg, IV, as directed, PRN other (see comment), drug form: inj"}, {"type": "category", "data": "Laboratory"}, {"type": "order", "data": "POC Arterial Plus Blood Gas", "value": ""}, {"type": "sentence", "data": "once, at 30 or 60 min after intubation"}, {"type": "order", "data": "POC Venous Plus Blood Gas", "value": ""}, {"type": "sentence", "data": "once, at 30 or 60 min after intubation"}, {"type": "order", "data": "POC Capillary Blood Gas", "value": ""}, {"type": "sentence", "data": "once, at 30 or 60 min after intubation"}, {"type": "category", "data": "Diagnostic Tests"}, {"type": "order", "data": "XR Chest", "value": ""}, {"type": "sentence", "data": "STAT, Transport: Portable"}, {"type": "category", "data": "Respiratory"}, {"type": "note", "data": "Select and modify ventilation settings as required. Refer to guideline: Oxygen Therapy: Guidelines for Monitoring", "value": ""}, {"type": "order", "data": "Invasive Ventilation", "value": ""}, {"type": "sentence", "data": "T;N"}, {"type": "order", "data": "High Frequency Jet Ventilation", "value": ""}, {"type": "sentence", "data": "T;N"}, {"type": "order", "data": "High Frequency Oscillatory Ventilation", "value": ""}, {"type": "sentence", "data": "T;N"}, {"type": "order", "data": "Insert Neurally Adjusted Ventilatory Assist Catheter", "value": ""}, {"type": "sentence", "data": "Insert and maintain NAVA catheter as per policy"}, {"type": "order", "data": "Neurally Adjusted Ventilatory Assist (NAVA)", "value": ""}, {"type": "sentence", "data": "T;N"}, {"type": "order", "data": "Neurally Adjusted Ventilatory Assist Catheter Care", "value": ""}, {"type": "sentence", "data": "T;N"}, {"type": "note", "data": "Monitoring", "value": ""}, {"type": "order", "data": "Transcutaneous Carbon Dioxide Monitoring TcPCO2", "value": ""}, {"type": "sentence", "data": "T;N"}, {"type": "order", "data": "End Tidal CO2 Monitoring", "value": ""}, {"type": "sentence", "data": "T;N"}]
