[{"type": "title", "data": "NICU Peripherally Inserted Central Catheter Insertion (Multiphase)"}, {"type": "sentence", "data": "None"}, {"type": "category", "data": "Patient Care"}, {"type": "note", "data": "Indications:  \n- IV medications requiring central access  \n- Antibiotic therapy greater than 7 days  \n- TPN greater than 7 days  \n- Malpositioned umbilical venous catheter (UVC)  \n- UVC in place for greater than 10 days  \n- Multiple venipunctures for peripheral intravenous (PIV)", "value": ""}, {"type": "note", "data": "Add patient to NICU - PICC Care Team and communicate with NICU PICC Nurse", "value": ""}, {"type": "note", "data": "If requesting PICC insertion by Radiology, select MI Venous Access (IR) Insert/Revision/Removal/Check Imaging Guided - Inpatient PowerPlan", "value": ""}, {"type": "order", "data": "NICU Insert Peripherally Inserted Central Catheter", "value": "checked"}, {"type": "sentence", "data": "Urgent, within 12 hours"}, {"type": "sentence", "data": "Urgent, within 24 hours"}, {"type": "sentence", "data": "Urgent, within 24 to 48 hours"}, {"type": "sentence", "data": "Urgent, within 48 to 72 hours"}, {"type": "order", "data": "Communication Order", "value": "checked"}, {"type": "sentence", "data": "Ensure parent/guardian consent done"}, {"type": "category", "data": "Medications"}, {"type": "sentence", "data": "None"}, {"type": "order", "data": "morphine", "value": ""}, {"type": "sentence", "data": "50 mcg/kg, IV, pre-procedure, drug form: inj"}, {"type": "order", "data": "fentanyl ", "value": ""}, {"type": "sentence", "data": "0.5 mcg/kg, IV, pre-procedure, drug form: inj"}, {"type": "sentence", "data": "1 mcg/kg, IV, pre-procedure, drug form: inj"}, {"type": "sentence", "data": "None"}, {"type": "category", "data": "Medications"}, {"type": "sentence", "data": "None"}, {"type": "note", "data": "Nurse to initiate Post Insertion Diagnostic Test phase of this PowerPlan once PICC has been inserted and XR required", "value": ""}, {"type": "sentence", "data": "None"}, {"type": "category", "data": "Medications"}, {"type": "sentence", "data": "None"}, {"type": "order", "data": "Omnipaque 300 [contrast media]", "value": "checked"}, {"type": "sentence", "data": "0.4 mL, IV, PRN other(see comment), as directed, order duration: 24 hour, drug form: inj"}, {"type": "category", "data": "Diagnostic Tests"}, {"type": "order", "data": "XR Chest", "value": ""}, {"type": "sentence", "data": "Urgent, Transport: Portable"}, {"type": "order", "data": "XR Chest", "value": ""}, {"type": "sentence", "data": "Timed, Transport: Portable"}, {"type": "order", "data": "XR Skull", "value": ""}, {"type": "sentence", "data": "Urgent, Transport: Portable"}, {"type": "order", "data": "XR Skull", "value": ""}, {"type": "sentence", "data": "Timed, Transport: Portable"}, {"type": "order", "data": "XR Chest/Abdomen single Exposure", "value": ""}, {"type": "sentence", "data": "Urgent, Transport: Portable"}, {"type": "order", "data": "XR Chest/Abdomen single Exposure", "value": ""}, {"type": "sentence", "data": "Timed, Transport: Portable"}, {"type": "sentence", "data": "None"}, {"type": "note", "data": "Nurse to initiate Follow Up Diagnostic Tests Phase after PICC insertion is completed", "value": ""}, {"type": "sentence", "data": "None"}, {"type": "order", "data": "XR Chest", "value": ""}, {"type": "sentence", "data": "Timed, Transport: Portable"}, {"type": "order", "data": "XR Skull", "value": ""}, {"type": "sentence", "data": "Timed, Transport: Portable"}, {"type": "order", "data": "XR Chest/Abdomen single Exposure", "value": ""}, {"type": "sentence", "data": "Timed, Transport: Portable"}]
