[{"type": "title", "data": "NICU Glucagon Administration for the Management of Persistent Hypoglycemia (Module)"}, {"type": "category", "data": "Medications"}, {"type": "note", "data": "Refer to Hypoglycemia Algorithm: Infant with Persistent Hypoglycemia Requiring Glucagon for Management ", "value": ""}, {"type": "sentence", "data": "None"}, {"type": "note", "data": "Consider starting glucagon if required Glucose Infusion Rate (GIR) was greater than 12 mg/kg/min during glucose stabilization", "value": ""}, {"type": "sentence", "data": "None"}, {"type": "order", "data": "glucagon NEO continuous infusion (40 mcg/mL) in D5W 25 mL", "value": ""}, {"type": "sentence", "data": "IV"}, {"type": "sentence", "data": "1 mg, 20 mcg/h"}, {"type": "sentence", "data": "24 mL"}, {"type": "note", "data": "Select glucagon bolus only during emergency rescue and/or consultation with Endocrinology", "value": ""}, {"type": "sentence", "data": "None"}, {"type": "order", "data": "glucagon (GLUCAGON)", "value": ""}, {"type": "sentence", "data": "30 mcg/kg, IM, once,drug form: kit"}, {"type": "order", "data": "glucagon (GLUCAGON)", "value": ""}, {"type": "sentence", "data": "30 mcg/kg, IV, once, drug form: kit"}, {"type": "category", "data": "Laboratory"}, {"type": "order", "data": "Electrolytes Urea Creatinine Panel", "value": "checked"}, {"type": "sentence", "data": "Blood, Urgent, Unit collect, Collection: T;N, once"}, {"type": "order", "data": "Calcium Ionized Whole Blood", "value": "checked"}, {"type": "sentence", "data": "Whole Blood, Urgent, Unit collect, Collection: T;N, once"}, {"type": "order", "data": "Capillary Blood Gas ", "value": "checked"}, {"type": "sentence", "data": "Whole Blood, Urgent, Collection: T;N, once"}, {"type": "order", "data": "Magnesium Level", "value": "checked"}, {"type": "sentence", "data": "Blood, Urgent, Unit collect, Collection: T;N, once"}, {"type": "order", "data": "CBC", "value": "checked"}, {"type": "sentence", "data": "Blood, Timed, Unit collect, Collection: T+1;N, once"}, {"type": "note", "data": "Repeating bloodwork:", "value": ""}, {"type": "order", "data": "CBC", "value": ""}, {"type": "sentence", "data": "Blood, Timed, Unit collect, Collection: T;N, q12h interval for 2 days"}, {"type": "sentence", "data": "Blood, Timed, Unit collect, Collection: T;N, q24h for 2 days"}, {"type": "order", "data": "Electrolytes Urea Creatinine Panel", "value": ""}, {"type": "sentence", "data": "Blood, Timed, Unit collect, Collection: T;N, q12h interval for 2 days"}, {"type": "sentence", "data": "Blood, Timed, Unit collect, Collection: T;N, q24h for 2 days"}, {"type": "order", "data": "Calcium Ionized Whole Blood", "value": ""}, {"type": "sentence", "data": "Whole Blood, Urgent, Unit collect, Collection: T;N, q12h interval for 2 days"}, {"type": "sentence", "data": "Whole Blood, Urgent, Unit collect, Collection: T;N, q24h interval for 2 days"}, {"type": "order", "data": "Calcium Ionized Whole Blood CWH", "value": ""}, {"type": "sentence", "data": "Whole Blood, Timed, Unit collect, Collection: T;N, q12h interval for 2 days"}, {"type": "sentence", "data": "Whole Blood, Timed, Unit collect, Collection: T;N, q24h for 2 days"}, {"type": "order", "data": "Capillary Blood Gas ", "value": ""}, {"type": "sentence", "data": "Whole Blood, Timed, Collection: T;N, q12h interval for 2 days"}, {"type": "sentence", "data": "Whole Blood, Timed, Collection: T;N, q24h for 2 days"}, {"type": "order", "data": "Magnesium Level", "value": ""}, {"type": "sentence", "data": "Blood, Timed, Unit collect, Collection: T;N, q12h interval for 2 days"}, {"type": "sentence", "data": "Blood, Timed, Unit collect, Collection: T;N, q24h for 2 days"}, {"type": "sentence", "data": "None"}, {"type": "sentence", "data": "None"}, {"type": "sentence", "data": "None"}, {"type": "sentence", "data": "None"}, {"type": "sentence", "data": "None"}, {"type": "sentence", "data": "None"}, {"type": "sentence", "data": "None"}, {"type": "sentence", "data": "None"}, {"type": "sentence", "data": "None"}, {"type": "sentence", "data": "None"}, {"type": "sentence", "data": "None"}, {"type": "sentence", "data": "None"}, {"type": "sentence", "data": "None"}, {"type": "sentence", "data": "None"}, {"type": "sentence", "data": "None"}, {"type": "sentence", "data": "None"}, {"type": "sentence", "data": "None"}, {"type": "sentence", "data": "None"}]
