[{"type": "title", "data": "PED NEPH Hemodialysis Initiation Treatment (Multiphase)"}, {"type": "category", "data": "Patient Care"}, {"type": "order", "data": "Hemodialysis", "value": "checked"}, {"type": "sentence", "data": "Please refer to HD Powerform for most recent HD prescription"}, {"type": "note", "data": "[Placeholder] PED Hemodialysis Order to link to HD PowerForm", "value": ""}, {"type": "note", "data": "Provide BP goal", "value": ""}, {"type": "order", "data": "Notify Treating Provider Vital Signs", "value": "checked"}, {"type": "sentence", "data": "Blood Pressure requirements"}, {"type": "order", "data": "Vital Signs", "value": "checked"}, {"type": "sentence", "data": "q15min, Respiratory rate, blood pressure and heart rate"}, {"type": "order", "data": "Hemodialysis / Pheresis Catheter Care", "value": "checked"}, {"type": "sentence", "data": "T;N"}, {"type": "category", "data": "Laboratory"}, {"type": "order", "data": "CBC and Differential", "value": "checked"}, {"type": "sentence", "data": "Blood, STAT, Unit collect, Collection: T;N, once, Collect pre-HD"}, {"type": "order", "data": "INR", "value": ""}, {"type": "sentence", "data": "Blood, STAT, Unit collect, Collection: T;N, once, Collect pre-HD"}, {"type": "order", "data": "Electrolytes Urea Creatinine Panel", "value": "checked"}, {"type": "sentence", "data": "Blood, STAT, Unit collect, Collection: T;N, once, Collect pre-HD"}, {"type": "order", "data": "Calcium Ionized Serum", "value": "checked"}, {"type": "sentence", "data": "Blood, STAT, Unit collect, Collection: T;N, once, Collect pre-HD"}, {"type": "order", "data": "Phosphate Level", "value": "checked"}, {"type": "sentence", "data": "Blood, STAT, Unit collect, Collection: T;N, once, Collect pre-HD"}, {"type": "order", "data": "Magnesium Level", "value": "checked"}, {"type": "sentence", "data": "Blood, STAT, Unit collect, Collection: T;N, once, Collect pre-HD"}, {"type": "order", "data": "Potassium Level", "value": "checked"}, {"type": "sentence", "data": "Blood, STAT, Unit collect, Collection: T;N, once, Collect pre-HD"}, {"type": "order", "data": "Albumin Level", "value": "checked"}, {"type": "sentence", "data": "Blood, STAT, Unit collect, Collection: T;N, once, Collect pre-HD"}, {"type": "order", "data": "Glucose Random", "value": "checked"}, {"type": "sentence", "data": "Blood, STAT, Unit collect, Collection: T;N, once, Collect pre-HD"}, {"type": "order", "data": "Parathyroid Hormone (PTH) Intact", "value": ""}, {"type": "sentence", "data": "Blood, STAT, Unit collect, Collection: T;N, once, Collect pre-HD"}, {"type": "order", "data": "Iron and Iron Binding Capacity Panel", "value": ""}, {"type": "sentence", "data": "Blood, STAT, Unit collect, Collection: T;N, once, Collect pre-HD"}, {"type": "order", "data": "Iron Transferrin Saturation Panel", "value": ""}, {"type": "sentence", "data": "Blood, STAT, Unit collect, Collection: T;N, once, Collect pre-HD"}, {"type": "order", "data": "Transferrin", "value": ""}, {"type": "sentence", "data": "Blood, STAT, Unit collect, Collection: T;N, once, Collect pre-HD"}, {"type": "order", "data": "Ferritin", "value": ""}, {"type": "sentence", "data": "Blood, STAT, Unit collect, Collection: T;N, once, Collect pre-HD"}, {"type": "order", "data": "Lactate Dehydrogenase", "value": ""}, {"type": "sentence", "data": "Blood, STAT, Unit collect, Collection: T;N, once, Collect pre-HD"}, {"type": "order", "data": "Alanine Aminotransferase", "value": ""}, {"type": "sentence", "data": "Blood, STAT, Unit collect, Collection: T;N, once, Collect pre-HD"}, {"type": "order", "data": "Gamma Glutamyl Transferase", "value": ""}, {"type": "sentence", "data": "Blood, STAT, Unit collect, Collection: T;N, once, Collect pre-HD"}, {"type": "order", "data": "Alkaline Phosphatase", "value": ""}, {"type": "sentence", "data": "Blood, STAT, Unit collect, Collection: T;N, once, Collect pre-HD"}, {"type": "order", "data": "Troponin I Cardiac High Sensitivity", "value": ""}, {"type": "sentence", "data": "Blood, STAT, Unit collect, Collection: T;N, once, Collect pre-HD"}, {"type": "order", "data": "Troponin T Cardiac High Sensitivity", "value": ""}, {"type": "sentence", "data": "Blood, STAT, Unit collect, Collection: T;N, once, Collect pre-HD"}, {"type": "order", "data": "Hemoglobin A1C", "value": ""}, {"type": "sentence", "data": "Blood, STAT, Unit collect, Collection: T;N, once, Collect pre-HD"}, {"type": "order", "data": "Cytotoxic Antibody Screen", "value": ""}, {"type": "sentence", "data": "Blood, STAT, Unit collect, Collection: T;N, once, Collect pre-HD"}, {"type": "note", "data": "If patient positive for Hepatitis B and C then uncheck Hepatitis B and C lab orders", "value": ""}, {"type": "order", "data": "Hepatitis B Core Antibody Total BCCDC", "value": "checked"}, {"type": "sentence", "data": "Blood, STAT, Unit collect, Collection: T;N, once, Collect pre-HD"}, {"type": "order", "data": "Hepatitis B Core Antibody Total PHC", "value": "checked"}, {"type": "sentence", "data": "Blood, STAT, Unit collect, Collection: T;N, once, Collect pre-HD"}, {"type": "order", "data": "Hepatitis B Surface Antibody BCCDC", "value": "checked"}, {"type": "sentence", "data": "Blood, STAT, Unit collect, Collection: T;N, once, Collect pre-HD"}, {"type": "order", "data": "Hepatitis B Surface Antibody PHC", "value": "checked"}, {"type": "sentence", "data": "Blood, STAT, Unit collect, Collection: T;N, once, Collect pre-HD"}, {"type": "order", "data": "Hepatitis B Surface Antigen BCCDC", "value": "checked"}, {"type": "sentence", "data": "Blood, STAT, Unit collect, Collection: T;N, once, Collect pre-HD"}, {"type": "order", "data": "Hepatitis B Surface Antigen PHC", "value": "checked"}, {"type": "sentence", "data": "Blood, STAT, Unit collect, Collection: T;N, once, Collect pre-HD"}, {"type": "order", "data": "Hepatitis C Antibody BCCDC", "value": "checked"}, {"type": "sentence", "data": "Blood, STAT, Unit collect, Collection: T;N, once, Collect pre-HD"}, {"type": "order", "data": "Hepatitis C Antibody PHC", "value": "checked"}, {"type": "sentence", "data": "Blood, STAT, Unit collect, Collection: T;N, once, Collect pre-HD"}, {"type": "order", "data": "HIV 1/2 Antibody and p24 Antigen BCCDC", "value": ""}, {"type": "sentence", "data": "Blood, STAT, Unit collect, Collection: T;N, once, Collect pre-HD"}, {"type": "order", "data": "HIV 1/2 Antibody and p24 Antigen PHC", "value": ""}, {"type": "sentence", "data": "Blood, STAT, Unit collect, Collection: T;N, once, Collect pre-HD"}, {"type": "note", "data": "Nurse to Initiate Post HD Labwork phase", "value": ""}, {"type": "order", "data": "Electrolytes Urea Creatinine Panel", "value": "checked"}, {"type": "sentence", "data": "Blood, STAT, Unit collect, Collection: T;N, once, Collect post-HD"}, {"type": "order", "data": "Calcium Ionized Serum", "value": "checked"}, {"type": "sentence", "data": "Blood, STAT, Unit collect, Collection: T;N, once, Collect post-HD"}, {"type": "order", "data": "Phosphate Level", "value": "checked"}, {"type": "sentence", "data": "Blood, STAT, Unit collect, Collection: T;N, once, Collect post-HD"}, {"type": "order", "data": "Magnesium Level", "value": "checked"}, {"type": "sentence", "data": "Blood, STAT, Unit collect, Collection: T;N, once, Collect post-HD"}, {"type": "order", "data": "Potassium Level", "value": "checked"}, {"type": "sentence", "data": "Blood, STAT, Unit collect, Collection: T;N, once, Collect post-HD"}, {"type": "order", "data": "Albumin Level", "value": "checked"}, {"type": "sentence", "data": "Blood, STAT, Unit collect, Collection: T;N, once, Collect post-HD"}, {"type": "order", "data": "Glucose Random", "value": "checked"}, {"type": "sentence", "data": "Blood, STAT, Unit collect, Collection: T;N, once, Collect post-HD"}, {"type": "category", "data": "Admit/Transfer/Discharge"}, {"type": "order", "data": "Schedule Hemodialysis", "value": "checked"}, {"type": "sentence", "data": "Hemodialysis, Initiation treatment qdaily for 3 sessions, Within 1 Week"}]
