[{"type": "title", "data": "=A1"}, {"type": "sentence", "data": "None"}, {"type": "note", "data": "Admit/Transfer/Discharge", "value": ""}, {"type": "sentence", "data": "None"}, {"type": "order", "data": "Discharge Patient", "value": ""}, {"type": "sentence", "data": "Discharge patient when they have stable vital signs for 1 hour and feel comfortable being discharged"}, {"type": "order", "data": "Discharge Patient Instructions", "value": ""}, {"type": "sentence", "data": "Discharge patient with prescriptions (if applicable) and instruction sheets"}, {"type": "order", "data": "Discharge Patient Instructions", "value": ""}, {"type": "sentence", "data": "Patient should be escorted home by friends or family"}, {"type": "note", "data": "Patient Care", "value": ""}, {"type": "sentence", "data": "None"}, {"type": "order", "data": "Insert Peripheral IV Catheter", "value": "checked"}, {"type": "sentence", "data": "T;N"}, {"type": "order", "data": "communication order", "value": ""}, {"type": "sentence", "data": "Assess for signs of an active infection and notify neurologist if concerns"}, {"type": "sentence", "data": "IF/WHEN the patient tolerated the infusion well, THEN it is not necessary for the physician to be on site for this observation period"}, {"type": "note", "data": "Medications", "value": ""}, {"type": "sentence", "data": "None"}, {"type": "note", "data": "Pre- Infusion Medications", "value": ""}, {"type": "sentence", "data": "None"}, {"type": "order", "data": "Hold medication(s)", "value": ""}, {"type": "sentence", "data": "Clinical event: Pre-infusion, Medication(s) to be held: antihypertensive, Instructions: HOLD dose 12 hours before infusion"}, {"type": "order", "data": "diphenhydrAMINE", "value": ""}, {"type": "sentence", "data": "50 mg, IV, once, drug form: inj"}, {"type": "order", "data": "diphenhydrAMINE", "value": ""}, {"type": "sentence", "data": "50 mg, PO, once, drug form: cap"}, {"type": "order", "data": "methylPREDNISolone (methylPREDNISolone sodium succinate)", "value": ""}, {"type": "sentence", "data": "100 mg, IV, once, drug form: inj"}, {"type": "order", "data": "ranitidine", "value": ""}, {"type": "sentence", "data": "50 mg, IV, once, drug form: inj"}, {"type": "order", "data": "ranitidine", "value": ""}, {"type": "sentence", "data": "150 mg, PO, once, drug form: tab"}, {"type": "order", "data": "acetaminophen", "value": ""}, {"type": "sentence", "data": "975 mg, PO, once, drug form: tab"}, {"type": "note", "data": "Biologic Agents", "value": ""}, {"type": "sentence", "data": "None"}, {"type": "order", "data": "PLACEHOLDER: ocrelizumab", "value": ""}, {"type": "sentence", "data": "600 mg, IV, once, administer over: 3.5 hours, drug form: bag, use patient supply"}, {"type": "order", "data": "Notify treating provider", "value": ""}, {"type": "sentence", "data": "Call on call physician, alert them to infusion reaction and provide supportive treatment as necessary"}, {"type": "note", "data": "Adverse Reaction Management", "value": ""}, {"type": "sentence", "data": "None"}, {"type": "sub phase", "data": "AMB Biologic Agents Infusion Reaction Protocol (Module)", "value": ""}, {"type": "sentence", "data": "None"}, {"type": "sentence", "data": "None"}, {"type": "note", "data": "Placeholder: Schedule Infusion - ocrelizumab\n", "value": ""}, {"type": "sentence", "data": "UBCH Medical Day Bed, Infusion, Routine"}, {"type": "sentence", "data": "Paper Referral, Infusion, Routine"}, {"type": "note", "data": "Placeholder: Schedule Infusion - ocrelizumab\n", "value": ""}, {"type": "sentence", "data": "UBCH Medical Day Bed, Infusion, Routine"}, {"type": "sentence", "data": "Paper Referral, Infusion, Routine"}, {"type": "sentence", "data": "None"}, {"type": "sentence", "data": "None"}, {"type": "sentence", "data": "None"}, {"type": "sentence", "data": "None"}, {"type": "sentence", "data": "None"}, {"type": "sentence", "data": "None"}, {"type": "sentence", "data": "None"}, {"type": "sentence", "data": "None"}, {"type": "sentence", "data": "None"}, {"type": "sentence", "data": "None"}, {"type": "sentence", "data": "None"}, {"type": "sentence", "data": "None"}, {"type": "sentence", "data": "None"}, {"type": "sentence", "data": "None"}, {"type": "sentence", "data": "None"}, {"type": "sentence", "data": "None"}, {"type": "sentence", "data": "None"}, {"type": "sentence", "data": "None"}, {"type": "sentence", "data": "None"}, {"type": "sentence", "data": "None"}, {"type": "sentence", "data": "None"}, {"type": "sentence", "data": "None"}, {"type": "sentence", "data": "None"}, {"type": "sentence", "data": "None"}, {"type": "sentence", "data": "None"}, {"type": "sentence", "data": "None"}, {"type": "sentence", "data": "None"}, {"type": "sentence", "data": "None"}, {"type": "sentence", "data": "None"}, {"type": "sentence", "data": "None"}, {"type": "sentence", "data": "None"}, {"type": "sentence", "data": "None"}, {"type": "sentence", "data": "None"}, {"type": "sentence", "data": "None"}, {"type": "sentence", "data": "None"}, {"type": "sentence", "data": "None"}, {"type": "sentence", "data": "None"}, {"type": "sentence", "data": "None"}, {"type": "sentence", "data": "None"}, {"type": "sentence", "data": "None"}, {"type": "sentence", "data": "None"}, {"type": "sentence", "data": "None"}, {"type": "sentence", "data": "None"}, {"type": "sentence", "data": "None"}, {"type": "sentence", "data": "None"}, {"type": "sentence", "data": "None"}, {"type": "sentence", "data": "None"}, {"type": "sentence", "data": "None"}, {"type": "sentence", "data": "None"}, {"type": "sentence", "data": "None"}, {"type": "sentence", "data": "None"}, {"type": "sentence", "data": "None"}, {"type": "sentence", "data": "None"}, {"type": "sentence", "data": "None"}, {"type": "sentence", "data": "None"}, {"type": "sentence", "data": "None"}, {"type": "sentence", "data": "None"}, {"type": "sentence", "data": "None"}, {"type": "sentence", "data": "None"}, {"type": "sentence", "data": "None"}, {"type": "sentence", "data": "None"}, {"type": "sentence", "data": "None"}, {"type": "sentence", "data": "None"}, {"type": "sentence", "data": "None"}, {"type": "sentence", "data": "None"}, {"type": "sentence", "data": "None"}, {"type": "sentence", "data": "None"}, {"type": "sentence", "data": "None"}, {"type": "sentence", "data": "None"}, {"type": "sentence", "data": "None"}, {"type": "sentence", "data": "None"}, {"type": "sentence", "data": "None"}, {"type": "sentence", "data": "None"}, {"type": "sentence", "data": "None"}, {"type": "sentence", "data": "None"}, {"type": "sentence", "data": "None"}, {"type": "sentence", "data": "None"}, {"type": "sentence", "data": "None"}, {"type": "sentence", "data": "None"}, {"type": "sentence", "data": "None"}, {"type": "sentence", "data": "None"}, {"type": "sentence", "data": "None"}, {"type": "sentence", "data": "None"}, {"type": "sentence", "data": "None"}, {"type": "sentence", "data": "None"}, {"type": "sentence", "data": "None"}, {"type": "sentence", "data": "None"}, {"type": "sentence", "data": "None"}, {"type": "sentence", "data": "None"}, {"type": "sentence", "data": "None"}, {"type": "sentence", "data": "None"}, {"type": "sentence", "data": "None"}, {"type": "sentence", "data": "None"}, {"type": "sentence", "data": "None"}, {"type": "sentence", "data": "None"}, {"type": "sentence", "data": "None"}, {"type": "sentence", "data": "None"}, {"type": "sentence", "data": "None"}, {"type": "sentence", "data": "None"}, {"type": "sentence", "data": "None"}, {"type": "sentence", "data": "None"}, {"type": "sentence", "data": "None"}, {"type": "sentence", "data": "None"}, {"type": "sentence", "data": "None"}, {"type": "sentence", "data": "None"}, {"type": "sentence", "data": "None"}, {"type": "sentence", "data": "None"}, {"type": "sentence", "data": "None"}, {"type": "sentence", "data": "None"}, {"type": "sentence", "data": "None"}, {"type": "sentence", "data": "None"}, {"type": "sentence", "data": "None"}, {"type": "sentence", "data": "None"}, {"type": "sentence", "data": "None"}, {"type": "sentence", "data": "None"}, {"type": "sentence", "data": "None"}, {"type": "sentence", "data": "None"}, {"type": "sentence", "data": "None"}, {"type": "sentence", "data": "None"}, {"type": "sentence", "data": "None"}, {"type": "sentence", "data": "None"}, {"type": "sentence", "data": "None"}, {"type": "sentence", "data": "None"}, {"type": "sentence", "data": "None"}, {"type": "sentence", "data": "None"}, {"type": "sentence", "data": "None"}, {"type": "sentence", "data": "None"}, {"type": "sentence", "data": "None"}, {"type": "sentence", "data": "None"}, {"type": "sentence", "data": "None"}, {"type": "sentence", "data": "None"}, {"type": "sentence", "data": "None"}, {"type": "sentence", "data": "None"}, {"type": "sentence", "data": "None"}, {"type": "sentence", "data": "None"}, {"type": "sentence", "data": "None"}, {"type": "sentence", "data": "None"}, {"type": "sentence", "data": "None"}, {"type": "sentence", "data": "None"}, {"type": "sentence", "data": "None"}, {"type": "sentence", "data": "None"}, {"type": "sentence", "data": "None"}, {"type": "sentence", "data": "None"}, {"type": "sentence", "data": "None"}, {"type": "sentence", "data": "None"}, {"type": "sentence", "data": "None"}, {"type": "sentence", "data": "None"}, {"type": "sentence", "data": "None"}, {"type": "sentence", "data": "None"}, {"type": "sentence", "data": "None"}, {"type": "sentence", "data": "None"}, {"type": "sentence", "data": "None"}, {"type": "sentence", "data": "None"}, {"type": "sentence", "data": "None"}, {"type": "sentence", "data": "None"}, {"type": "sentence", "data": "None"}, {"type": "sentence", "data": "None"}, {"type": "sentence", "data": "None"}, {"type": "sentence", "data": "None"}, {"type": "sentence", "data": "None"}, {"type": "sentence", "data": "None"}, {"type": "sentence", "data": "None"}, {"type": "sentence", "data": "None"}, {"type": "sentence", "data": "None"}, {"type": "sentence", "data": "None"}, {"type": "sentence", "data": "None"}, {"type": "sentence", "data": "None"}, {"type": "sentence", "data": "None"}, {"type": "sentence", "data": "None"}, {"type": "sentence", "data": "None"}, {"type": "sentence", "data": "None"}, {"type": "sentence", "data": "None"}, {"type": "sentence", "data": "None"}, {"type": "sentence", "data": "None"}, {"type": "sentence", "data": "None"}, {"type": "sentence", "data": "None"}, {"type": "sentence", "data": "None"}, {"type": "sentence", "data": "None"}, {"type": "sentence", "data": "None"}, {"type": "sentence", "data": "None"}, {"type": "sentence", "data": "None"}, {"type": "sentence", "data": "None"}, {"type": "sentence", "data": "None"}, {"type": "sentence", "data": "None"}, {"type": "sentence", "data": "None"}, {"type": "sentence", "data": "None"}, {"type": "sentence", "data": "None"}, {"type": "sentence", "data": "None"}, {"type": "sentence", "data": "None"}, {"type": "sentence", "data": "None"}, {"type": "sentence", "data": "None"}, {"type": "sentence", "data": "None"}, {"type": "sentence", "data": "None"}, {"type": "sentence", "data": "None"}, {"type": "sentence", "data": "None"}, {"type": "sentence", "data": "None"}, {"type": "sentence", "data": "None"}, {"type": "sentence", "data": "None"}, {"type": "sentence", "data": "None"}, {"type": "sentence", "data": "None"}, {"type": "sentence", "data": "None"}, {"type": "sentence", "data": "None"}, {"type": "sentence", "data": "None"}, {"type": "sentence", "data": "None"}, {"type": "sentence", "data": "None"}, {"type": "sentence", "data": "None"}, {"type": "sentence", "data": "None"}, {"type": "sentence", "data": "None"}, {"type": "sentence", "data": "None"}, {"type": "sentence", "data": "None"}, {"type": "sentence", "data": "None"}, {"type": "sentence", "data": "None"}, {"type": "sentence", "data": "None"}, {"type": "sentence", "data": "None"}, {"type": "sentence", "data": "None"}, {"type": "sentence", "data": "None"}, {"type": "sentence", "data": "None"}, {"type": "sentence", "data": "None"}, {"type": "sentence", "data": "None"}, {"type": "sentence", "data": "None"}, {"type": "sentence", "data": "None"}, {"type": "sentence", "data": "None"}, {"type": "sentence", "data": "None"}, {"type": "sentence", "data": "None"}, {"type": "sentence", "data": "None"}, {"type": "sentence", "data": "None"}, {"type": "sentence", "data": "None"}, {"type": "sentence", "data": "None"}, {"type": "sentence", "data": "None"}, {"type": "sentence", "data": "None"}, {"type": "sentence", "data": "None"}, {"type": "sentence", "data": "None"}, {"type": "sentence", "data": "None"}, {"type": "sentence", "data": "None"}, {"type": "sentence", "data": "None"}, {"type": "sentence", "data": "None"}, {"type": "sentence", "data": "None"}, {"type": "sentence", "data": "None"}, {"type": "sentence", "data": "None"}, {"type": "sentence", "data": "None"}, {"type": "sentence", "data": "None"}, {"type": "sentence", "data": "None"}, {"type": "sentence", "data": "None"}, {"type": "sentence", "data": "None"}, {"type": "sentence", "data": "None"}, {"type": "sentence", "data": "None"}, {"type": "sentence", "data": "None"}, {"type": "sentence", "data": "None"}, {"type": "sentence", "data": "None"}, {"type": "sentence", "data": "None"}, {"type": "sentence", "data": "None"}, {"type": "sentence", "data": "None"}, {"type": "sentence", "data": "None"}, {"type": "sentence", "data": "None"}, {"type": "sentence", "data": "None"}, {"type": "sentence", "data": "None"}, {"type": "sentence", "data": "None"}, {"type": "sentence", "data": "None"}, {"type": "sentence", "data": "None"}, {"type": "sentence", "data": "None"}, {"type": "sentence", "data": "None"}, {"type": "sentence", "data": "None"}, {"type": "sentence", "data": "None"}, {"type": "sentence", "data": "None"}, {"type": "sentence", "data": "None"}, {"type": "sentence", "data": "None"}, {"type": "sentence", "data": "None"}, {"type": "sentence", "data": "None"}, {"type": "sentence", "data": "None"}, {"type": "sentence", "data": "None"}, {"type": "sentence", "data": "None"}, {"type": "sentence", "data": "None"}, {"type": "sentence", "data": "None"}, {"type": "sentence", "data": "None"}, {"type": "sentence", "data": "None"}, {"type": "sentence", "data": "None"}, {"type": "sentence", "data": "None"}, {"type": "sentence", "data": "None"}, {"type": "sentence", "data": "None"}, {"type": "sentence", "data": "None"}, {"type": "sentence", "data": "None"}, {"type": "sentence", "data": "None"}, {"type": "sentence", "data": "None"}, {"type": "sentence", "data": "None"}, {"type": "sentence", "data": "None"}, {"type": "sentence", "data": "None"}, {"type": "sentence", "data": "None"}, {"type": "sentence", "data": "None"}, {"type": "sentence", "data": "None"}, {"type": "sentence", "data": "None"}, {"type": "sentence", "data": "None"}, {"type": "sentence", "data": "None"}, {"type": "sentence", "data": "None"}, {"type": "sentence", "data": "None"}]
